osplo/OSLOpen.py
osplo/__init__.py
osplo-0.1.12.dist-info/LICENSE.txt
osplo-0.1.12.dist-info/METADATA
osplo-0.1.12.dist-info/WHEEL
osplo-0.1.12.dist-info/top_level.txt
osplo-0.1.12.dist-info/RECORD
