Metadata-Version: 2.1
Name: osplo
Version: 0.1.12
Summary: Stellt einen langsamen Iterator über Textdateien (komprimiert, txt, online) zur Verfügung, der einen Satz pro Iteration zurückliefert.
Home-page: https://github.com/miweru/osplo
Author: Michael Ruppert
Author-email: michael.ruppert@fau.de
License: GNU GENERAL PUBLIC LICENSE V3 OR LATER (GPLV3+)
Platform: UNKNOWN
Classifier: Programming Language :: Python :: 3
Classifier: License :: OSI Approved :: GNU General Public License v3 or later (GPLv3+)
Classifier: Topic :: Software Development :: Libraries :: Python Modules
Classifier: Topic :: Text Processing :: Linguistic
Requires-Python: >=3.5
Requires-Dist: somajo (>=1.8.3)
Requires-Dist: smart-open (>=1.8.0)
